Metadata-Version: 2.1
Name: pftag
Version: 1.0.2
Summary: A tag parser with optional functional support
Home-page: https://github.com/FNNDSC/pftag
Author: FNNDSC
Author-email: rudolph.pienaar@childrens.harvard.edu
License: MIT
Platform: UNKNOWN
Classifier: License :: OSI Approved :: MIT License
Classifier: Topic :: Scientific/Engineering
Classifier: Topic :: Scientific/Engineering :: Bio-Informatics
Classifier: Topic :: Scientific/Engineering :: Medical Science Apps.
Provides-Extra: none
Provides-Extra: dev
License-File: LICENSE
